kemptech_openstack_lbaas
tests
