Metadata-Version: 1.1
Name: kemptech-openstack-lbaas
Version: 1.0.7
Summary: KEMP Technologies OpenStack LBaaS Driver V2
Home-page: http://pypi.python.org/pypi/kemptech-openstack-lbaas/
Author: Shane McGough
Author-email: smcgough@kemptechnologies.com
License: Apache
Keywords: kemptech kemp technologies lbaas load balancer driver
Platform: UNKNOWN
Classifier: License :: OSI Approved :: Apache Software License
Classifier: Operating System :: POSIX
Classifier: Programming Language :: Python
Classifier: Programming Language :: Python :: 2.7
Classifier: Programming Language :: Python :: 3
Classifier: Topic :: Internet
